atig
