Metadata-Version: 2.1
Name: atig
Version: 0.0.2
Summary: Alembic migration history viewer
Home-page: https://github.com/djentleman/atig
Author: Todd Perry
Author-email: todd.perry@myport.ac.uk
License: UNKNOWN
Platform: UNKNOWN
Classifier: Programming Language :: Python :: 3
Classifier: License :: OSI Approved :: MIT License
Classifier: Operating System :: OS Independent
Requires-Python: >=3.6
